{
  "adapter-name": "sklearn",
  "job-file-name": "sklearn-job.json",
  "env-varname-cluster": "RUNTIME",
  "grpc-server-address": "127.0.0.1",
  "export-zip-file-name": "sklearn-export",
  "training-path": "/home/alex/Desktop/MetaAutoML/adapters/AutoSklearn/app-data/training",
  "job-folder-name": "job",
  "model-folder-name": "model",
  "export-folder-name": "export",
  "result-folder-name": "result",
  "templates-path": "app-data/templates",
  "predict-time-sources-path": "../Utils/AutoMLs/predict_time_sources.py",
  "local_execution": "YES"
}